Metadata-Version: 2.1
Name: apprise
Version: 1.9.2
Summary: Push Notifications that work with just about every platform!
Home-page: https://github.com/caronc/apprise
Author: Chris Caron
Author-email: lead2gold@gmail.com
License: BSD 2-Clause
Keywords: Africas Talking Alerts Apprise API Automated Packet Reporting System AWS BulkSMS BulkVS Burst SMS Chanify Chat CLI ClickSend D7Networks Dapnet DBus DingTalk Discord Email Emby Enigma2 FCM Feishu Flock Form Free Mobile Gnome Google Chat Gotify Growl Guilded Home Assistant httpSMS IFTTT Join JSON Kavenegar KODI Kumulos LaMetric Line LunaSea MacOSX Mailgun Mastodon Matrix Mattermost MessageBird Microsoft Misskey MQTT MSG91 MSTeams Nextcloud NextcloudTalk Notica Notifiarr Notifico Ntfy Off
Classifier: Development Status :: 5 - Production/Stable
Classifier: Intended Audience :: Developers
Classifier: Intended Audience :: System Administrators
Classifier: Operating System :: OS Independent
Classifier: Natural Language :: English
Classifier: Programming Language :: Python
Classifier: Programming Language :: Python :: 3
Classifier: Programming Language :: Python :: 3.6
Classifier: Programming Language :: Python :: 3.7
Classifier: Programming Language :: Python :: 3.8
Classifier: Programming Language :: Python :: 3.9
Classifier: Programming Language :: Python :: 3.10
Classifier: Programming Language :: Python :: 3.11
Classifier: Programming Language :: Python :: 3.12
Classifier: Programming Language :: Python :: Implementation :: CPython
Classifier: Programming Language :: Python :: Implementation :: PyPy
Classifier: License :: OSI Approved :: BSD License
Classifier: Topic :: Software Development :: Libraries :: Python Modules
Classifier: Topic :: Software Development :: Libraries :: Application Frameworks
Requires-Python: >=3.6
License-File: LICENSE
Requires-Dist: certifi
Requires-Dist: requests
Requires-Dist: requests-oauthlib
Requires-Dist: click>=5.0
Requires-Dist: markdown
Requires-Dist: PyYAML
